{
  "symbol": "ETHUSDT",
  "interval": "15m",
  "objective": "sharpe",
  "constraints": {
    "min_trades": 80,
    "min_trades_per_day": 0.25,
    "min_sharpe": 0.2,
    "max_drawdown_limit": -0.3,
    "min_return": 0.03
  },
  "data_split": {
    "train_ratio": 0.65,
    "val_ratio": 0.82
  },
  "constraint_passed_count": 0,
  "search_space": {
    "position_mode": "long_short",
    "device_type": "cuda",
    "gpu_platform_id": 0,
    "gpu_device_id": 0,
    "gpu_use_dp": 0,
    "horizons": [
      1,
      2,
      3,
      4,
      6
    ],
    "target_thresholds": [
      0.0,
      0.0003,
      0.0006,
      0.001,
      0.0015
    ],
    "learning_rates": [
      0.01,
      0.02,
      0.03,
      0.05
    ],
    "num_leaves": [
      15,
      31,
      63,
      127
    ],
    "buy": [
      0.52,
      0.62,
      0.02
    ],
    "sell": [
      0.38,
      0.48,
      0.02
    ]
  },
  "best": {
    "horizon": 4,
    "target_threshold": 0.0003,
    "learning_rate": 0.01,
    "num_leaves": 127,
    "best_iteration": 31,
    "n_features": 55,
    "train_samples": 115810,
    "val_samples": 30289,
    "test_samples": 32071,
    "buy_threshold": 0.54,
    "sell_threshold": 0.38,
    "val_strategy_total_return": 0.001210470897436533,
    "val_sharpe": 0.4843584338696908,
    "trades_turnover_count": 4,
    "exposure_ratio": 9.354245268310935e-05,
    "trades_per_day": 0.005986716971718998,
    "constraint_passed": false,
    "strategy_total_return": 0.004412463968192171,
    "benchmark_total_return": 0.1465428904308963,
    "annualized_return": 0.004821934896929836,
    "annualized_volatility": 0.004323605823097646,
    "sharpe": 1.1152577487915312,
    "max_drawdown": -0.0006000000000000449,
    "closed_trades": 2,
    "win_rate": 1.0,
    "avg_trade_return": 0.002204058396410802,
    "median_trade_return": 0.002204058396410802,
    "clf_accuracy": 0.5214991737083347,
    "clf_precision": 0.5627240143369175,
    "clf_recall": 0.07048938490154576
  },
  "top10": [
    {
      "horizon": 4,
      "target_threshold": 0.0003,
      "learning_rate": 0.01,
      "num_leaves": 127,
      "best_iteration": 31,
      "n_features": 55,
      "train_samples": 115810,
      "val_samples": 30289,
      "test_samples": 32071,
      "buy_threshold": 0.54,
      "sell_threshold": 0.38,
      "val_strategy_total_return": 0.001210470897436533,
      "val_sharpe": 0.4843584338696908,
      "trades_turnover_count": 4,
      "exposure_ratio": 9.354245268310935e-05,
      "trades_per_day": 0.005986716971718998,
      "constraint_passed": false,
      "strategy_total_return": 0.004412463968192171,
      "benchmark_total_return": 0.1465428904308963,
      "annualized_return": 0.004821934896929836,
      "annualized_volatility": 0.004323605823097646,
      "sharpe": 1.1152577487915312,
      "max_drawdown": -0.0006000000000000449,
      "closed_trades": 2,
      "win_rate": 1.0,
      "avg_trade_return": 0.002204058396410802,
      "median_trade_return": 0.002204058396410802,
      "clf_accuracy": 0.5214991737083347,
      "clf_precision": 0.5627240143369175,
      "clf_recall": 0.07048938490154576
    },
    {
      "horizon": 4,
      "target_threshold": 0.0,
      "learning_rate": 0.05,
      "num_leaves": 31,
      "best_iteration": 16,
      "n_features": 55,
      "train_samples": 115810,
      "val_samples": 30289,
      "test_samples": 32071,
      "buy_threshold": 0.6,
      "sell_threshold": 0.42,
      "val_strategy_total_return": 0.0009288253573338512,
      "val_sharpe": 0.061354525703554555,
      "trades_turnover_count": 64,
      "exposure_ratio": -0.0018084874185401141,
      "trades_per_day": 0.09578747154750397,
      "constraint_passed": false,
      "strategy_total_return": 0.02364402328079418,
      "benchmark_total_return": 0.1465428904308963,
      "annualized_return": 0.02586096118274761,
      "annualized_volatility": 0.027511026635026494,
      "sharpe": 0.9400216693411924,
      "max_drawdown": -0.019780031070678383,
      "closed_trades": 32,
      "win_rate": 0.78125,
      "avg_trade_return": 0.0007374941807298946,
      "median_trade_return": 0.0011171102047569104,
      "clf_accuracy": 0.5201895793707711,
      "clf_precision": 0.5313437907016252,
      "clf_recall": 0.56883904213398
    },
    {
      "horizon": 6,
      "target_threshold": 0.0,
      "learning_rate": 0.03,
      "num_leaves": 127,
      "best_iteration": 27,
      "n_features": 55,
      "train_samples": 115810,
      "val_samples": 30289,
      "test_samples": 32071,
      "buy_threshold": 0.6,
      "sell_threshold": 0.38,
      "val_strategy_total_return": -0.02535635305393802,
      "val_sharpe": -0.9800451721191374,
      "trades_turnover_count": 30,
      "exposure_ratio": 0.0012784135200024946,
      "trades_per_day": 0.044900377287892486,
      "constraint_passed": false,
      "strategy_total_return": 0.03853973921424858,
      "benchmark_total_return": 0.1465428904308963,
      "annualized_return": 0.04218184506938538,
      "annualized_volatility": 0.06220590424886265,
      "sharpe": 0.6781003439903636,
      "max_drawdown": -0.02311727256824614,
      "closed_trades": 15,
      "win_rate": 0.4,
      "avg_trade_return": 0.002627623116557524,
      "median_trade_return": -0.0007260499951703414,
      "clf_accuracy": 0.5204390259112593,
      "clf_precision": 0.5313056049822064,
      "clf_recall": 0.5788804071246819
    },
    {
      "horizon": 6,
      "target_threshold": 0.0,
      "learning_rate": 0.01,
      "num_leaves": 127,
      "best_iteration": 72,
      "n_features": 55,
      "train_samples": 115810,
      "val_samples": 30289,
      "test_samples": 32071,
      "buy_threshold": 0.58,
      "sell_threshold": 0.38,
      "val_strategy_total_return": 0.003814675712775717,
      "val_sharpe": 0.11941674411464956,
      "trades_turnover_count": 50,
      "exposure_ratio": 0.0022450188643946246,
      "trades_per_day": 0.07483396214648748,
      "constraint_passed": false,
      "strategy_total_return": 0.03827900637841575,
      "benchmark_total_return": 0.1465428904308963,
      "annualized_return": 0.04189597896671393,
      "annualized_volatility": 0.06497202689000163,
      "sharpe": 0.6448310291695886,
      "max_drawdown": -0.03139136178619628,
      "closed_trades": 25,
      "win_rate": 0.52,
      "avg_trade_return": 0.0015709829724070668,
      "median_trade_return": 0.00016285154768214127,
      "clf_accuracy": 0.5207820149044308,
      "clf_precision": 0.5308380797396257,
      "clf_recall": 0.5928753180661578
    },
    {
      "horizon": 4,
      "target_threshold": 0.0,
      "learning_rate": 0.01,
      "num_leaves": 63,
      "best_iteration": 127,
      "n_features": 55,
      "train_samples": 115810,
      "val_samples": 30289,
      "test_samples": 32071,
      "buy_threshold": 0.6,
      "sell_threshold": 0.38,
      "val_strategy_total_return": -0.029386025345388367,
      "val_sharpe": -0.5633274301964452,
      "trades_turnover_count": 116,
      "exposure_ratio": 0.00021826572292725515,
      "trades_per_day": 0.17361479217985096,
      "constraint_passed": false,
      "strategy_total_return": 0.035031866622868835,
      "benchmark_total_return": 0.1465428904308963,
      "annualized_return": 0.038336389342080945,
      "annualized_volatility": 0.06463189445056038,
      "sharpe": 0.5931497083286958,
      "max_drawdown": -0.030340151213526623,
      "closed_trades": 58,
      "win_rate": 0.4482758620689655,
      "avg_trade_return": 0.0006239695056461381,
      "median_trade_return": -8.147072912784159e-05,
      "clf_accuracy": 0.5185058152224752,
      "clf_precision": 0.5317608734994269,
      "clf_recall": 0.5344043649590785
    },
    {
      "horizon": 1,
      "target_threshold": 0.0,
      "learning_rate": 0.05,
      "num_leaves": 15,
      "best_iteration": 43,
      "n_features": 55,
      "train_samples": 115810,
      "val_samples": 30289,
      "test_samples": 32071,
      "buy_threshold": 0.6,
      "sell_threshold": 0.38,
      "val_strategy_total_return": 0.0,
      "val_sharpe": 0.0,
      "trades_turnover_count": 12,
      "exposure_ratio": 0.00021826572292725515,
      "trades_per_day": 0.017960150915156993,
      "constraint_passed": false,
      "strategy_total_return": 0.002589397555564643,
      "benchmark_total_return": 0.1465428904308963,
      "annualized_return": 0.0028294520545002477,
      "annualized_volatility": 0.006171759966251292,
      "sharpe": 0.4584514093179888,
      "max_drawdown": -0.004338930998210033,
      "closed_trades": 6,
      "win_rate": 0.6666666666666666,
      "avg_trade_return": 0.0004333198990001767,
      "median_trade_return": 0.0007832719188106685,
      "clf_accuracy": 0.5315705777805494,
      "clf_precision": 0.5354359253217328,
      "clf_recall": 0.5471721412694492
    },
    {
      "horizon": 6,
      "target_threshold": 0.0003,
      "learning_rate": 0.05,
      "num_leaves": 31,
      "best_iteration": 7,
      "n_features": 55,
      "train_samples": 115810,
      "val_samples": 30289,
      "test_samples": 32071,
      "buy_threshold": 0.54,
      "sell_threshold": 0.38,
      "val_strategy_total_return": 0.0,
      "val_sharpe": 0.0,
      "trades_turnover_count": 2,
      "exposure_ratio": 3.118081756103645e-05,
      "trades_per_day": 0.002993358485859499,
      "constraint_passed": false,
      "strategy_total_return": 0.00047592963356613005,
      "benchmark_total_return": 0.1465428904308963,
      "annualized_return": 0.0005200006762742237,
      "annualized_volatility": 0.0012882667962047197,
      "sharpe": 0.40364362242833896,
      "max_drawdown": -0.0006000000000000449,
      "closed_trades": 1,
      "win_rate": 1.0,
      "avg_trade_return": 0.00047592963356613005,
      "median_trade_return": 0.00047592963356613005,
      "clf_accuracy": 0.5206261108166256,
      "clf_precision": 0.5349129420211811,
      "clf_recall": 0.18905030768254774
    },
    {
      "horizon": 3,
      "target_threshold": 0.0,
      "learning_rate": 0.05,
      "num_leaves": 127,
      "best_iteration": 5,
      "n_features": 55,
      "train_samples": 115810,
      "val_samples": 30289,
      "test_samples": 32071,
      "buy_threshold": 0.56,
      "sell_threshold": 0.38,
      "val_strategy_total_return": 0.0,
      "val_sharpe": 0.0,
      "trades_turnover_count": 4,
      "exposure_ratio": 6.23616351220729e-05,
      "trades_per_day": 0.005986716971718998,
      "constraint_passed": false,
      "strategy_total_return": 0.001960013633945046,
      "benchmark_total_return": 0.1465428904308963,
      "annualized_return": 0.0021416577260269243,
      "annualized_volatility": 0.005688345974810711,
      "sharpe": 0.37649920302152357,
      "max_drawdown": -0.002466589114048512,
      "closed_trades": 2,
      "win_rate": 0.5,
      "avg_trade_return": 0.0009854796212070416,
      "median_trade_return": 0.0009854796212070416,
      "clf_accuracy": 0.5227775872283371,
      "clf_precision": 0.5276545977291555,
      "clf_recall": 0.6586374695863747
    },
    {
      "horizon": 3,
      "target_threshold": 0.0003,
      "learning_rate": 0.05,
      "num_leaves": 63,
      "best_iteration": 10,
      "n_features": 55,
      "train_samples": 115810,
      "val_samples": 30289,
      "test_samples": 32071,
      "buy_threshold": 0.54,
      "sell_threshold": 0.38,
      "val_strategy_total_return": 0.013273187034030798,
      "val_sharpe": 0.3359672273841903,
      "trades_turnover_count": 6,
      "exposure_ratio": 9.354245268310935e-05,
      "trades_per_day": 0.008980075457578496,
      "constraint_passed": false,
      "strategy_total_return": 0.002285031137193805,
      "benchmark_total_return": 0.1465428904308963,
      "annualized_return": 0.0024968337091646475,
      "annualized_volatility": 0.008552591067286874,
      "sharpe": 0.2919388626816124,
      "max_drawdown": -0.0061301151706539825,
      "closed_trades": 3,
      "win_rate": 0.6666666666666666,
      "avg_trade_return": 0.0007711353125526843,
      "median_trade_return": 0.003409292812988296,
      "clf_accuracy": 0.5238377350254124,
      "clf_precision": 0.5348001796138303,
      "clf_recall": 0.07720731232983274
    },
    {
      "horizon": 1,
      "target_threshold": 0.0,
      "learning_rate": 0.02,
      "num_leaves": 31,
      "best_iteration": 120,
      "n_features": 55,
      "train_samples": 115810,
      "val_samples": 30289,
      "test_samples": 32071,
      "buy_threshold": 0.62,
      "sell_threshold": 0.38,
      "val_strategy_total_return": 0.0,
      "val_sharpe": 0.0,
      "trades_turnover_count": 4,
      "exposure_ratio": 6.23616351220729e-05,
      "trades_per_day": 0.005986716971718998,
      "constraint_passed": false,
      "strategy_total_return": 0.0013571254835318403,
      "benchmark_total_return": 0.1465428904308963,
      "annualized_return": 0.0014828556318524644,
      "annualized_volatility": 0.005219261135316942,
      "sharpe": 0.2841121747709635,
      "max_drawdown": -0.0031466794403850473,
      "closed_trades": 2,
      "win_rate": 0.5,
      "avg_trade_return": 0.0006835512557307188,
      "median_trade_return": 0.0006835512557307188,
      "clf_accuracy": 0.5299179944498145,
      "clf_precision": 0.5349257827117375,
      "clf_recall": 0.5295752037540133
    }
  ]
}